Workbook

Sheet How To
A1: How to use this calculator
A2: Only edit BLUE cells (yellow fill = the main settings). Black cells are formulas, green cells pull values from another sheet. Click a link in column C to jump to the cell.
A4: 1. Add a sensor
A5: 1 | B5: Go to the Sensors sheet and find the first empty row (rows 6–205). | C5: =HYPERLINK("#'Sensors'!B21","→ Sensors!B21") -> → Sensors!B21
A6: 2 | B6: Type the Device ID exactly as in Akvo_Green config.json → devices[].id (for example DEV_16). Upper/lower case and length matter: the name is sent in every message.
A7: 3 | B7: Type the Sensor name exactly as in config.json → devices[].sensors[].name (for example FlowSensor).
A8: 4 | B8: Type 1 in Active. Columns E and F fill in by themselves.
A9: 5 | B9: Several sensors on the same device: repeat the same Device ID on each row; the device is only counted once.
A10: 6 | B10: Check the result: Summary → Active sensors, Data message size, Monthly cost per site. | C10: =HYPERLINK("#'Summary'!A1","→ Summary!A1") -> → Summary!A1
A12: 2. Remove or pause a sensor
A13: 1 | B13: Set Active to 0 to leave the sensor out but keep the row (useful for what-if comparisons), or delete the Device ID and Sensor name.
A14: 2 | B14: Do not delete whole rows or columns: the formulas expect the list in rows 6–205.
A16: 3. Change the sampling frequency
A17: 1 | B17: Sensor data interval: seconds between data messages (gateway.poll_interval in config.json). One message carries ALL sensors. | C17: =HYPERLINK("#'Inputs'!C7","→ Inputs!C7") -> → Inputs!C7
A18: 2 | B18: System data interval: seconds between CPU/RAM/disk messages (gateway.system_interval). | C18: =HYPERLINK("#'Inputs'!C8","→ Inputs!C8") -> → Inputs!C8
A19: 3 | B19: Example: 20 → 10 s doubles the data messages, IoT messages, rule actions and S3 writes; 20 → 60 s cuts them to a third.
A20: 4 | B20: Keep the dashboard poll in line: if the data interval is longer than the live poll, the dashboard polls for data that is not there yet. | C20: =HYPERLINK("#'Inputs'!C17","→ Inputs!C17") -> → Inputs!C17
A22: 4. Model several sites (several Pis)
A23: 1 | B23: Set Number of sites. Every site is its own stack (bucket, API, dashboard) and its own SIM, so AWS cost and data plan are multiplied. | C23: =HYPERLINK("#'Inputs'!C11","→ Inputs!C11") -> → Inputs!C11
A24: 2 | B24: The Sensors sheet describes ONE site. If the sites have very different sensors, make a copy of the file per site.
A26: 5. Describe how the dashboard is used
A27: 1 | B27: Dashboards open at the same time and Hours per day open drive API Gateway and Lambda (each open dashboard polls every 10 s). | C27: =HYPERLINK("#'Inputs'!C15","→ Inputs!C15") -> → Inputs!C15
A28: 2 | B28: A control-room screen open all day: Hours per day open = 24. | C28: =HYPERLINK("#'Inputs'!C16","→ Inputs!C16") -> → Inputs!C16
A29: 3 | B29: History / alarm queries per day and their average range in days drive Athena and S3 GET cost. | C29: =HYPERLINK("#'Inputs'!C19","→ Inputs!C19") -> → Inputs!C19
A30: 4 | B30: Tests per month and their duration drive report generation. | C30: =HYPERLINK("#'Inputs'!C24","→ Inputs!C24") -> → Inputs!C24
A32: 6. Update AWS prices
A33: 1 | B33: Open the Prices sheet and compare each blue price with the AWS page in the Source column (region us-east-1). | C33: =HYPERLINK("#'Prices'!A1","→ Prices!A1") -> → Prices!A1
A34: 2 | B34: Type the new price over the old one; keep the same unit as the 'Per' column (e.g. price per million requests, not per request).
A35: 3 | B35: Optional: Apply AWS always-free tier = Yes subtracts the always-free allowances. They are per AWS account, so with several sites leave it on No for a safe estimate. | C35: =HYPERLINK("#'Inputs'!C30","→ Inputs!C30") -> → Inputs!C30
A37: 7. Size the Pi's cellular data plan
A38: 1 | B38: Open the Data Plan sheet. Gateway traffic is taken from your sensors and intervals automatically. | C38: =HYPERLINK("#'Data Plan'!C7","→ Data Plan!C7") -> → Data Plan!C7
A39: 2 | B39: OS updates: 0 if automatic updates are disabled on the Pi; about 300 MB/month if they stay on. | C39: =HYPERLINK("#'Data Plan'!C17","→ Data Plan!C17") -> → Data Plan!C17
A40: 3 | B40: MQTT reconnects per day: raise it if the cellular signal is weak (check the gateway log for 'Connecting MQTT'). | C40: =HYPERLINK("#'Data Plan'!C10","→ Data Plan!C10") -> → Data Plan!C10
A41: 4 | B41: Carrier minimum per session: ask the carrier whether data sessions are rounded up (M2M/IoT SIMs sometimes are). 0 = billed by actual usage. | C41: =HYPERLINK("#'Data Plan'!C18","→ Data Plan!C18") -> → Data Plan!C18
A42: 5 | B42: Enter the carrier's plans in MB from smallest to largest, with their monthly price. The recommended plan is the smallest one that fits. | C42: =HYPERLINK("#'Data Plan'!C35","→ Data Plan!C35") -> → Data Plan!C35
A43: 6 | B43: Read the result: Data needed per Pi and Recommended plan per Pi. | C43: =HYPERLINK("#'Data Plan'!C43","→ Data Plan!C43") -> → Data Plan!C43
A45: 8. Check the estimate against reality
A46: 1 | B46: Data used by the Pi: on the Pi run sudo apt install vnstat and after a few days vnstat -m (or read /sys/class/net/<interface>/statistics/rx_bytes and tx_bytes). Compare with Data needed per Pi before the margin (Subtotal).
A47: 2 | B47: Messages really sent: AWS console → IoT Core → Monitor, or CloudWatch metric AWS/IoT PublishIn.Success. Compare with Calculation → MQTT messages per month.
A48: 3 | B48: Real AWS cost: AWS console → Billing → Cost Explorer, group by Service, last full month. Compare service by service with the table on the Summary sheet.
A49: 4 | B49: If something differs a lot, adjust the matching grey technical constant on the Inputs sheet (for example API Lambda duration or log volume).
A51: 9. Read the results
A52: 1 | B52: Summary → Monthly cost per site (yellow) is the main figure; the table and chart show which services cost the most. | C52: =HYPERLINK("#'Summary'!A1","→ Summary!A1") -> → Summary!A1
A53: 2 | B53: Calculation shows every intermediate quantity with how it is calculated, and the full cost table (usage → free allowance → billable → price → cost). | C53: =HYPERLINK("#'Calculation'!A1","→ Calculation!A1") -> → Calculation!A1
A54: 3 | B54: Storage figures are for the month after 'Months of history kept', because raw data in S3 and Lambda logs are never deleted.
A56: 10. Rebuild the file from scratch
A57: 1 | B57: The workbook is generated by tools/build_cost_calculator.py in the VenkoDemo repo: python3 tools/build_cost_calculator.py docs/aws_cost_calculator.xlsx
A58: 2 | B58: Rebuilding overwrites every change made in the file (sensors, inputs, prices). Change the defaults in the script if you want them to survive a rebuild.
A59: 3 | B59: Open the rebuilt file in Excel or LibreOffice once and save it, so the calculated values are stored.

Sheet Summary
A1: VenkoDemo / Akvo_Green — AWS cost calculator
A2: How to use: edit sensors on 'Sensors' (Active 1/0), intervals and usage on 'Inputs' (yellow cells), unit prices on 'Prices'. Size the Pi's cellular plan on 'Data Plan'. Everything else recalculates. Region us-east-1, prices to be verified before quoting.
A4: Key inputs
A5: Active sensors | B5: =active_sensors -> 15 | D5: From the Sensors sheet
A6: Sensor data interval (s) | B6: =poll_s -> 20 | D6: Inputs
A7: System data interval (s) | B7: =sys_s -> 60 | D7: Inputs
A8: Sites | B8: =sites -> 1 | D8: Inputs
A9: Data volume per site
A10: Data message size (bytes) | B10: =data_payload_b -> 1236 | D10: JSON payload with all active sensors
A11: MQTT messages per month | B11: =msgs_month -> 175200 | D11: Data + system
A12: Payload per month (MB) | B12: =payload_month_mb -> 176.4264 | D12: JSON only
A13: Network traffic per month (MB) | B13: =wire_month_mb -> 217.3356 | D13: Gateway MQTT only, incl. MQTT/TLS/TCP overhead and acks
A14: New S3 raw data per month (GB) | B14: =raw_gb_month -> 0.1718156
A15: Cellular data plan per Pi
A16: Data needed per Pi (MB/month) | B16: =dp_required_mb -> 339.47387 | D16: Data Plan sheet: gateway + other Pi traffic + margin
A17: Recommended plan | B17: =dp_plan -> 500 MB | D17: Smallest plan on the Data Plan sheet that covers it
A18: Cost
A19: Monthly cost per site | B19: =cost_site_month -> 3.4717019 | D19: Calculation sheet, at the 'months kept' storage horizon
A20: Monthly cost, all sites | B20: =cost_site_month*sites -> 3.4717019
A21: Yearly cost, all sites | B21: =cost_site_month*sites*12 -> 41.660423 | D21: Storage grows each month; this uses the horizon month ×12 (upper bound)
A22: Cost per active sensor per month | B22: =IFERROR(cost_site_month/active_sensors,0) -> 0.2314468 | D22: Includes the fixed per-site costs spread over the sensors
A24: Monthly cost per site by service
A25: Service | B25: USD / month | C25: Share
A26: IoT Core | B26: =SUMIF(Calculation!$A$72:$A$97,A26,Calculation!$H$72:$H$97) -> 0.257544 | C26: =IFERROR(B26/cost_site_month,0) -> 0.074183788
A27: Data Firehose | B27: =SUMIF(Calculation!$A$72:$A$97,A27,Calculation!$H$72:$H$97) -> 0.024227142 | C27: =IFERROR(B27/cost_site_month,0) -> 0.0069784627
A28: S3 | B28: =SUMIF(Calculation!$A$72:$A$97,A28,Calculation!$H$72:$H$97) -> 2.2417576 | C28: =IFERROR(B28/cost_site_month,0) -> 0.64572295
A29: Athena | B29: =SUMIF(Calculation!$A$72:$A$97,A29,Calculation!$H$72:$H$97) -> 0.034285629 | C29: =IFERROR(B29/cost_site_month,0) -> 0.0098757409
A30: Glue | B30: =SUMIF(Calculation!$A$72:$A$97,A30,Calculation!$H$72:$H$97) -> 0.0026213333 | C30: =IFERROR(B30/cost_site_month,0) -> 0.00075505714
A31: Lambda | B31: =SUMIF(Calculation!$A$72:$A$97,A31,Calculation!$H$72:$H$97) -> 0.17476257 | C31: =IFERROR(B31/cost_site_month,0) -> 0.050339164
A32: API Gateway | B32: =SUMIF(Calculation!$A$72:$A$97,A32,Calculation!$H$72:$H$97) -> 0.62091108 | C32: =IFERROR(B32/cost_site_month,0) -> 0.17884919
A33: DynamoDB | B33: =SUMIF(Calculation!$A$72:$A$97,A33,Calculation!$H$72:$H$97) -> 0.011334042 | C33: =IFERROR(B33/cost_site_month,0) -> 0.0032646932
A34: CloudFront | B34: =SUMIF(Calculation!$A$72:$A$97,A34,Calculation!$H$72:$H$97) -> 0.0057213534 | C34: =IFERROR(B34/cost_site_month,0) -> 0.0016479967
A35: Data transfer | B35: =SUMIF(Calculation!$A$72:$A$97,A35,Calculation!$H$72:$H$97) -> 0.025782622 | C35: =IFERROR(B35/cost_site_month,0) -> 0.0074265081
A36: CloudWatch Logs | B36: =SUMIF(Calculation!$A$72:$A$97,A36,Calculation!$H$72:$H$97) -> 0.07275454 | C36: =IFERROR(B36/cost_site_month,0) -> 0.020956448
A37: EventBridge | B37: =SUMIF(Calculation!$A$72:$A$97,A37,Calculation!$H$72:$H$97) -> 0 | C37: =IFERROR(B37/cost_site_month,0) -> 0
A38: IAM / API keys / usage plan | B38: =SUMIF(Calculation!$A$72:$A$97,A38,Calculation!$H$72:$H$97) -> 0 | C38: =IFERROR(B38/cost_site_month,0) -> 0
A39: Total | B39: =SUM(B26:B38) -> 3.4717019

Sheet Sensors
A1: Sensor list (one row per sensor published by the Akvo_Green gateway)
A2: Edit the blue cells: Device ID and Sensor name exactly as in Akvo_Green config.json, Active = 1 to include, 0 to exclude. Add sensors in the empty rows below (up to row 205). Pre-filled from Akvo_Green/config_data/config.json (15 sensors).
A3: Name lengths matter: every reading repeats the device and sensor name in the MQTT JSON payload.
A5: # | B5: Device ID | C5: Sensor name | D5: Active (1/0) | E5: Bytes per reading | F5: Device bytes (first sensor of device)
A6: 1 | B6: DEV_1 | C6: Pt100Sensor | D6: 1 | E6: =IF(AND(D6=1,C6<>""),LEN(C6)+sensor_over_b,0) -> 66 | F6: =IF(AND(E6>0,COUNTIFS(B$6:B6,B6,D$6:D6,1,C$6:C6,"<>")=1),LEN(B6)+device_over_b,0) -> 13
A7: 2 | B7: DEV_2 | C7: Ambient | D7: 1 | E7: =IF(AND(D7=1,C7<>""),LEN(C7)+sensor_over_b,0) -> 62 | F7: =IF(AND(E7>0,COUNTIFS(B$6:B7,B7,D$6:D7,1,C$6:C7,"<>")=1),LEN(B7)+device_over_b,0) -> 13
A8: 3 | B8: DEV_3 | C8: Humedad | D8: 1 | E8: =IF(AND(D8=1,C8<>""),LEN(C8)+sensor_over_b,0) -> 62 | F8: =IF(AND(E8>0,COUNTIFS(B$6:B8,B8,D$6:D8,1,C$6:C8,"<>")=1),LEN(B8)+device_over_b,0) -> 13
A9: 4 | B9: DEV_4 | C9: ORPSensor | D9: 1 | E9: =IF(AND(D9=1,C9<>""),LEN(C9)+sensor_over_b,0) -> 64 | F9: =IF(AND(E9>0,COUNTIFS(B$6:B9,B9,D$6:D9,1,C$6:C9,"<>")=1),LEN(B9)+device_over_b,0) -> 13
A10: 5 | B10: DEV_5 | C10: PhSensor | D10: 1 | E10: =IF(AND(D10=1,C10<>""),LEN(C10)+sensor_over_b,0) -> 63 | F10: =IF(AND(E10>0,COUNTIFS(B$6:B10,B10,D$6:D10,1,C$6:C10,"<>")=1),LEN(B10)+device_over_b,0) -> 13
A11: 6 | B11: DEV_6 | C11: TempPhSensor | D11: 1 | E11: =IF(AND(D11=1,C11<>""),LEN(C11)+sensor_over_b,0) -> 67 | F11: =IF(AND(E11>0,COUNTIFS(B$6:B11,B11,D$6:D11,1,C$6:C11,"<>")=1),LEN(B11)+device_over_b,0) -> 13
A12: 7 | B12: DEV_7 | C12: DOSensor | D12: 1 | E12: =IF(AND(D12=1,C12<>""),LEN(C12)+sensor_over_b,0) -> 63 | F12: =IF(AND(E12>0,COUNTIFS(B$6:B12,B12,D$6:D12,1,C$6:C12,"<>")=1),LEN(B12)+device_over_b,0) -> 13
A13: 8 | B13: DEV_8 | C13: CODSensor | D13: 1 | E13: =IF(AND(D13=1,C13<>""),LEN(C13)+sensor_over_b,0) -> 64 | F13: =IF(AND(E13>0,COUNTIFS(B$6:B13,B13,D$6:D13,1,C$6:C13,"<>")=1),LEN(B13)+device_over_b,0) -> 13
A14: 9 | B14: DEV_9 | C14: TempCODSensor | D14: 1 | E14: =IF(AND(D14=1,C14<>""),LEN(C14)+sensor_over_b,0) -> 68 | F14: =IF(AND(E14>0,COUNTIFS(B$6:B14,B14,D$6:D14,1,C$6:C14,"<>")=1),LEN(B14)+device_over_b,0) -> 13
A15: 10 | B15: DEV_10 | C15: TurbCODSensort | D15: 1 | E15: =IF(AND(D15=1,C15<>""),LEN(C15)+sensor_over_b,0) -> 69 | F15: =IF(AND(E15>0,COUNTIFS(B$6:B15,B15,D$6:D15,1,C$6:C15,"<>")=1),LEN(B15)+device_over_b,0) -> 14
A16: 11 | B16: DEV_11 | C16: BODSensor | D16: 1 | E16: =IF(AND(D16=1,C16<>""),LEN(C16)+sensor_over_b,0) -> 64 | F16: =IF(AND(E16>0,COUNTIFS(B$6:B16,B16,D$6:D16,1,C$6:C16,"<>")=1),LEN(B16)+device_over_b,0) -> 14
A17: 12 | B17: DEV_12 | C17: TOCSensor | D17: 1 | E17: =IF(AND(D17=1,C17<>""),LEN(C17)+sensor_over_b,0) -> 64 | F17: =IF(AND(E17>0,COUNTIFS(B$6:B17,B17,D$6:D17,1,C$6:C17,"<>")=1),LEN(B17)+device_over_b,0) -> 14
... A20: 15 | B20: DEV_15 | C20: TDSCondSensor | D20: 1 | E20: =IF(AND(D20=1,C20<>""),LEN(C20)+sensor_over_b,0) -> 68 | F20: =IF(AND(E20>0,COUNTIFS(B$6:B20,B20,D$6:D20,1,C$6:C20,"<>")=1),LEN(B20)+device_over_b,0) -> 14
A21: 16 | E21: =IF(AND(D21=1,C21<>""),LEN(C21)+sensor_over_b,0) -> 0 | F21: =IF(AND(E21>0,COUNTIFS(B$6:B21,B21,D$6:D21,1,C$6:C21,"<>")=1),LEN(B21)+device_over_b,0) -> 0
A22: 17 | E22: =IF(AND(D22=1,C22<>""),LEN(C22)+sensor_over_b,0) -> 0 | F22: =IF(AND(E22>0,COUNTIFS(B$6:B22,B22,D$6:D22,1,C$6:C22,"<>")=1),LEN(B22)+device_over_b,0) -> 0
A23: 18 | E23: =IF(AND(D23=1,C23<>""),LEN(C23)+sensor_over_b,0) -> 0 | F23: =IF(AND(E23>0,COUNTIFS(B$6:B23,B23,D$6:D23,1,C$6:C23,"<>")=1),LEN(B23)+device_over_b,0) -> 0
A24: 19 | E24: =IF(AND(D24=1,C24<>""),LEN(C24)+sensor_over_b,0) -> 0 | F24: =IF(AND(E24>0,COUNTIFS(B$6:B24,B24,D$6:D24,1,C$6:C24,"<>")=1),LEN(B24)+device_over_b,0) -> 0
A25: 20 | E25: =IF(AND(D25=1,C25<>""),LEN(C25)+sensor_over_b,0) -> 0 | F25: =IF(AND(E25>0,COUNTIFS(B$6:B25,B25,D$6:D25,1,C$6:C25,"<>")=1),LEN(B25)+device_over_b,0) -> 0
A26: 21 | E26: =IF(AND(D26=1,C26<>""),LEN(C26)+sensor_over_b,0) -> 0 | F26: =IF(AND(E26>0,COUNTIFS(B$6:B26,B26,D$6:D26,1,C$6:C26,"<>")=1),LEN(B26)+device_over_b,0) -> 0
A27: 22 | E27: =IF(AND(D27=1,C27<>""),LEN(C27)+sensor_over_b,0) -> 0 | F27: =IF(AND(E27>0,COUNTIFS(B$6:B27,B27,D$6:D27,1,C$6:C27,"<>")=1),LEN(B27)+device_over_b,0) -> 0
A28: 23 | E28: =IF(AND(D28=1,C28<>""),LEN(C28)+sensor_over_b,0) -> 0 | F28: =IF(AND(E28>0,COUNTIFS(B$6:B28,B28,D$6:D28,1,C$6:C28,"<>")=1),LEN(B28)+device_over_b,0) -> 0
A29: 24 | E29: =IF(AND(D29=1,C29<>""),LEN(C29)+sensor_over_b,0) -> 0 | F29: =IF(AND(E29>0,COUNTIFS(B$6:B29,B29,D$6:D29,1,C$6:C29,"<>")=1),LEN(B29)+device_over_b,0) -> 0
A30: 25 | E30: =IF(AND(D30=1,C30<>""),LEN(C30)+sensor_over_b,0) -> 0 | F30: =IF(AND(E30>0,COUNTIFS(B$6:B30,B30,D$6:D30,1,C$6:C30,"<>")=1),LEN(B30)+device_over_b,0) -> 0
A31: 26 | E31: =IF(AND(D31=1,C31<>""),LEN(C31)+sensor_over_b,0) -> 0 | F31: =IF(AND(E31>0,COUNTIFS(B$6:B31,B31,D$6:D31,1,C$6:C31,"<>")=1),LEN(B31)+device_over_b,0) -> 0
A32: 27 | E32: =IF(AND(D32=1,C32<>""),LEN(C32)+sensor_over_b,0) -> 0 | F32: =IF(AND(E32>0,COUNTIFS(B$6:B32,B32,D$6:D32,1,C$6:C32,"<>")=1),LEN(B32)+device_over_b,0) -> 0
... A205: 200 | E205: =IF(AND(D205=1,C205<>""),LEN(C205)+sensor_over_b,0) -> 0 | F205: =IF(AND(E205>0,COUNTIFS(B$6:B205,B205,D$6:D205,1,C$6:C205,"<>")=1),LEN(B205)+device_over_b,0) -> 0

Sheet Inputs
A1: Inputs and assumptions (per site)
A2: Blue = value you can change · yellow fill = main levers · grey section = technical constants derived from the code (change only if the code changes).
A4: Parameter | B4: Name | C4: Value | D4: Unit | E4: Source / note
A6: Gateway (Akvo_Green config.json → gateway section)
A7: Sensor data interval | B7: poll_s | C7: 20 | D7: seconds | E7: gateway.poll_interval — one data message with ALL sensors per interval
A8: System data interval | B8: sys_s | C8: 60 | D8: seconds | E8: gateway.system_interval — CPU/RAM/disk/IP/OS message
A9: Data topic | B9: topic_data | C9: AKVO/data | D9: text | E9: aws.topic_pub (stack DataTopic). Its length is part of every MQTT packet
A10: System topic | B10: topic_sys | C10: AKVO/system | D10: text | E10: aws.topic_system (stack SystemTopic)
A11: Number of sites (Pi + stack + dashboard) | B11: sites | C11: 1 | D11: sites | E11: Each site is a full separate stack; the total is multiplied by this
A12: Days per month | B12: days_month | C12: =365/12 -> 30.416667 | D12: days | E12: Average month
A14: Dashboard usage
A15: Dashboards open at the same time (average) | B15: viewers | C15: 1 | D15: browsers | E15: Each open dashboard polls /live + /tests/active
A16: Hours per day a dashboard is open | B16: hours_open | C16: 8 | D16: hours/day | E16: Left open 24 h on a control-room screen = 24
A17: Live poll interval | B17: live_poll_s | C17: 10 | D17: seconds | E17: LIVE_POLL_MS in web/js/main.js
A18: Dashboard page loads | B18: page_loads | C18: 10 | D18: loads/day | E18: Each load downloads web/ through CloudFront (caching disabled) and calls config/active/lists
A19: History / alarm queries | B19: history_q | C19: 20 | D19: queries/day | E19: Every History or Alarms view refresh runs one Athena query
A20: Average query range | B20: history_days | C20: 1 | D20: days | E20: Range selected in History/Alarms (max 31 days, MAX_RANGE_DAYS)
A21: Excel/CSV exports | B21: exports | C21: 10 | D21: exports/month | E21: GET /export runs one Athena query
A23: Tests and reports
A24: Tests per month | B24: tests_month | C24: 8 | D24: tests/month | E24: Each Start/Stop test produces one report (3 Athena queries)
A25: Average test duration | B25: test_hours | C25: 4 | D25: hours | E25: Report queries scan whole days
A26: Weekly reports per month | B26: weekly_reports | C26: =52/12 -> 4.3333333 | D26: reports/month | E26: EventBridge every Monday
A28: Retention and pricing options
A29: Months of history kept in S3 / CloudWatch | B29: months_kept | C29: 12 | D29: months | E29: Raw data never expires (bucket Retain, no expiry rule). Storage cost shown is the month after this many months
A30: Apply AWS always-free tier | B30: free_tier | C30: No | D30: Yes/No | E30: Yes = subtract always-free allowances (Lambda, CloudFront, CloudWatch, DynamoDB storage, Glue, data transfer). One allowance per AWS account, shared by all sites | F30: =IF(C30="Yes",1,0) -> 0
A32: Technical constants (from the code - change only if the code changes)
A33: Data payload fixed part | B33: data_base_b | C33: 57 | D33: bytes | E33: json.dumps({"ts": "<ISO time>", "devices": {}}) in edge_node_improved.publisher()
A34: Per-sensor overhead (+ sensor name length) | B34: sensor_over_b | C34: 55 | D34: bytes | E34: "<name>": {"val": 23.45, "status": "OK", "alarm": "NORMAL"}, — 53 B + 2 B separator
A35: Per-device overhead (+ device id length) | B35: device_over_b | C35: 8 | D35: bytes | E35: "<device>": {...}, — 6 B + 2 B separator
A36: System payload | B36: sys_payload_b | C36: 320 | D36: bytes | E36: get_system_status(): ts, gateway, city, city_time, platform, cpu/ram/disk, ip, os
A37: Fields added by the IoT rule | B37: iot_added_b | C37: 46 | D37: bytes | E37: SELECT *, clientid() AS gw, timestamp() AS rx_ms — stored in S3, read by Athena
A38: TLS record overhead | B38: tls_b | C38: 29 | D38: bytes/packet | E38: TLS 1.2 AES-GCM: 5 header + 8 nonce + 16 tag
A39: TCP/IP header overhead | B39: tcpip_b | C39: 52 | D39: bytes/packet | E39: IPv4 20 + TCP 20 + timestamps option 12
A40: Firehose buffer interval | B40: fh_buffer_s | C40: 60 | D40: seconds | E40: BufferingHints IntervalInSeconds in infra/template.yaml → one S3 object per stream per minute
A41: Athena minimum billed per query | B41: athena_min_mb | C41: 10 | D41: MB | E41: Athena bills at least 10 MB per query
A42: API calls per page load | B42: api_per_load | C42: 5 | D42: requests | E42: config, live, tests/active, tests list, reports list
A43: API calls per test | B43: api_per_test | C43: 8 | D43: requests | E43: start, stop, comments, report status polls
A44: DynamoDB writes per test | B44: ddb_writes_test | C44: 10 | D44: writes | E44: test item, ACTIVE state put/delete, comments, report status
... A58: Glue catalog requests per Athena query | B58: glue_per_query | C58: 4 | D58: requests | E58: Estimate: GetDatabase/GetTable/GetPartitions

Sheet Prices
A1: AWS unit prices — us-east-1 (N. Virginia), on-demand, USD
A2: Prices are list prices as known when this file was built (Oct 2026) and are NOT fetched live. Check each against the source link before quoting; edit the blue cells to update every calculation.
A4: Service | B4: Item | C4: Price | D4: Per | E4: Always-free allowance (per account / month) | F4: Source
A5: IoT Core | B5: Connectivity | C5: 0.08 | D5: million connection-minutes | E5: 0 | F5: https://aws.amazon.com/iot-core/pricing/
A6: IoT Core | B6: Messaging (5 KB increments) | C6: 1 | D6: million messages | E6: 0 | F6: https://aws.amazon.com/iot-core/pricing/
A7: IoT Core | B7: Rules triggered | C7: 0.15 | D7: million rules | E7: 0 | F7: https://aws.amazon.com/iot-core/pricing/
A8: IoT Core | B8: Rule actions executed | C8: 0.15 | D8: million actions | E8: 0 | F8: https://aws.amazon.com/iot-core/pricing/
A9: Data Firehose | B9: Direct PUT ingestion (5 KB record rounding) | C9: 0.029 | D9: GB ingested | E9: 0 | F9: https://aws.amazon.com/firehose/pricing/
A10: S3 | B10: Standard storage | C10: 0.023 | D10: GB-month | E10: 0 | F10: https://aws.amazon.com/s3/pricing/
A11: S3 | B11: PUT / COPY / POST / LIST requests | C11: 0.005 | D11: 1,000 requests | E11: 0 | F11: https://aws.amazon.com/s3/pricing/
A12: S3 | B12: GET / SELECT requests | C12: 0.0004 | D12: 1,000 requests | E12: 0 | F12: https://aws.amazon.com/s3/pricing/
A13: Athena | B13: Data scanned (10 MB min per query) | C13: 5 | D13: TB scanned | E13: 0 | F13: https://aws.amazon.com/athena/pricing/
A14: Glue | B14: Data Catalog requests | C14: 1 | D14: million requests | E14: 1 | F14: https://aws.amazon.com/glue/pricing/
A15: Lambda | B15: Requests | C15: 0.2 | D15: million requests | E15: 1 | F15: https://aws.amazon.com/lambda/pricing/
A16: Lambda | B16: Compute, arm64 | C16: 1.33334e-05 | D16: GB-second | E16: 400000 | F16: https://aws.amazon.com/lambda/pricing/
... A27: IAM / API keys / usage plan | B27: No charge | C27: 0 | D27: - | E27: 0 | F27: -
A29: Not included: IoT Device Management/Defender (not used), Route 53 (no custom domain), taxes, support plans.
A30: IoT data sent INTO AWS has no transfer charge. S3 lifecycle rule raw/→Standard-IA after 90 days does not apply: since Sept 2024 S3 skips transitions of objects < 128 KB, and Firehose writes ~1 small object per minute, so raw data stays in Standard.
A31: AWS 12-month free tier / new-account credits are not modelled; only always-free allowances (toggle on the Inputs sheet).

Sheet Calculation
A1: Traffic and usage (per site, per month unless noted)
A2: All cells are formulas — edit Sensors, Inputs or Prices instead.
A4: Quantity | B4: Name | C4: Value | D4: Unit | E4: How it is calculated
A6: Sensors and payloads
A7: Active sensors | B7: active_sensors | C7: =COUNTIFS(Sensors!$D$6:$D$205,1,Sensors!$C$6:$C$205,"<>") -> 15 | D7: sensors | E7: Rows on Sensors with Active = 1
A8: Devices with active sensors | B8: active_devices | C8: =COUNTIF(Sensors!$F$6:$F$205,">0") -> 15 | D8: devices | E8: Distinct Device IDs
A9: Data message payload | B9: data_payload_b | C9: =data_base_b+SUM(Sensors!$E$6:$E$205)+SUM(Sensors!$F$6:$F$205) -> 1236 | D9: bytes | E9: Fixed part + every active sensor + every device wrapper
A10: System message payload | B10: sys_payload | C10: =sys_payload_b -> 320 | D10: bytes | E10: Independent of sensor count
A11: Data messages per day | B11: data_msgs_day | C11: =86400/poll_s -> 4320 | D11: messages/day | E11: 86,400 s ÷ data interval
A12: System messages per day | B12: sys_msgs_day | C12: =86400/sys_s -> 1440 | D12: messages/day | E12: 86,400 s ÷ system interval
A14: Network traffic Pi ↔ AWS IoT (MQTT over TLS, QoS 1)
A15: Data packet on the wire (upload) | B15: data_up_b | C15: =data_payload_b+6+LEN(topic_data)+tls_b+tcpip_b -> 1332 | D15: bytes | E15: Payload + MQTT header (fixed 2 + topic length 2 + topic + packet id 2) + TLS + TCP/IP
A16: System packet on the wire (upload) | B16: sys_up_b | C16: =sys_payload+6+LEN(topic_sys)+tls_b+tcpip_b -> 418 | D16: bytes | E16: Same, for the system topic
A17: PUBACK received per message (download) | B17: ack_down_b | C17: =4+tls_b+tcpip_b -> 85 | D17: bytes | E17: QoS 1 acknowledgement from AWS
A18: TCP ACK sent per message (upload) | B18: ack_up_b | C18: =tcpip_b -> 52 | D18: bytes | E18: Pi acknowledges the PUBACK segment
A19: Payload per day | B19: payload_day_mb | C19: =(data_msgs_day*data_payload_b+sys_msgs_day*sys_payload)/1000000 -> 5.80032 | D19: MB/day | E19: JSON only
A20: Total on the wire per day | B20: wire_day_mb | C20: =(data_msgs_day*(data_up_b+ack_down_b+ack_up_b)+sys_msgs_day*(sys_up_b+ack_down_b+ack_up_b))/1000000 -> 7.14528 | D20: MB/day | E20: Upload + download, all overhead included (excludes rare TLS reconnects, ~7 KB each)
A21: Payload per month | B21: payload_month_mb | C21: =payload_day_mb*days_month -> 176.4264 | D21: MB/month
A22: Total on the wire per month | B22: wire_month_mb | C22: =wire_day_mb*days_month -> 217.3356 | D22: MB/month | E22: Use this to size the Pi's mobile data plan
A23: MQTT messages per month | B23: msgs_month | C23: =(data_msgs_day+sys_msgs_day)*days_month -> 175200 | D23: messages
A24: IoT billed messages per month | B24: iot_billed_month | C24: =(data_msgs_day*ROUNDUP(data_payload_b/5120,0)+sys_msgs_day*ROUNDUP(sys_payload/5120,0))*days_month -> 175200 | D24: messages | E24: Each message billed per started 5 KB; above ~90 sensors a data message counts twice
A26: Storage pipeline (IoT rules → Firehose → S3, plus latest/*.json)
A27: Stored data record | B27: data_rec_b | C27: =data_payload_b+iot_added_b -> 1282 | D27: bytes | E27: Payload + gw + rx_ms added by the IoT rule
A28: Stored system record | B28: sys_rec_b | C28: =sys_payload+iot_added_b -> 366 | D28: bytes
A29: Raw data bytes per day (data table) | B29: raw_day_data | C29: =data_msgs_day*data_rec_b -> 5538240 | D29: bytes/day | E29: What Athena scans per day of history
A30: Raw data bytes per day (system table) | B30: raw_day_sys | C30: =sys_msgs_day*sys_rec_b -> 527040 | D30: bytes/day
A31: New raw data per month | B31: raw_gb_month | C31: =(raw_day_data+raw_day_sys)*days_month/1073741824 -> 0.1718156 | D31: GB/month | E31: Uncompressed JSON (Firehose CompressionFormat UNCOMPRESSED)
A32: Firehose billed volume | B32: fh_gb_month | C32: =(data_msgs_day*ROUNDUP(data_rec_b/5120,0)+sys_msgs_day*ROUNDUP(sys_rec_b/5120,0))*5120*days_month/1073741824 -> 0.8354187 | D32: GB/month | E32: Every record rounded up to 5 KB — small records cost far more than their size
A33: S3 objects per day, data stream | B33: objs_day_data | C33: =MIN(data_msgs_day,86400/fh_buffer_s) -> 1440 | D33: objects/day | E33: One object per buffer interval while data flows
A34: S3 objects per day, system stream | B34: objs_day_sys | C34: =MIN(sys_msgs_day,86400/fh_buffer_s) -> 1440 | D34: objects/day
A35: Firehose S3 PUTs per month | B35: fh_puts_month | C35: =(objs_day_data+objs_day_sys)*days_month -> 87600 | D35: requests
A36: latest/*.json S3 PUTs per month | B36: latest_puts_month | C36: =msgs_month -> 175200 | D36: requests | E36: IoT rule S3 action overwrites latest/data.json or latest/system.json on EVERY message
A37: S3 storage at retention horizon | B37: s3_store_gb | C37: =raw_gb_month*months_kept+(tests_month+weekly_reports)*report_mb*months_kept/1024 -> 2.0906935 | D37: GB | E37: Raw history + reports after 'months kept'; grows linearly forever (no expiry)
A39: Dashboard and API
A40: Live polls per month | B40: live_polls | C40: =viewers*hours_open*3600/live_poll_s*days_month -> 87600 | D40: polls | E40: Each poll = GET /live + GET /tests/active
A41: Page loads per month | B41: page_loads_month | C41: =page_loads*days_month -> 304.16667 | D41: loads
A42: History/alarm queries per month | B42: history_month | C42: =history_q*days_month -> 608.33333 | D42: queries
A43: Reports per month | B43: reports_month | C43: =tests_month+weekly_reports -> 12.333333 | D43: reports | E43: Test reports + weekly reports
A44: Simple API requests | B44: api_simple | C44: =live_polls*2+page_loads_month*api_per_load+tests_month*api_per_test -> 176784.83 | D44: requests | E44: No Athena involved
A45: Athena-backed API requests | B45: api_athena | C45: =history_month+exports -> 618.33333 | D45: requests | E45: /history, /alarms, /export
A46: API Gateway requests | B46: api_requests | C46: =api_simple+api_athena -> 177403.17 | D46: requests
A47: Lambda invocations | B47: lambda_inv | C47: =api_requests+reports_month -> 177415.5 | D47: invocations | E47: API function + report function
A48: Lambda compute | B48: lambda_gbs | C48: =(api_simple*api_ms/1000+api_athena*athena_ms/1000)*api_mem_mb/1024+reports_month*report_s*report_mem_mb/1024 -> 10445.908 | D48: GB-seconds | E48: Duration × memory
A49: API response data out | B49: api_out_gb | C49: =(live_polls*(live_base_b+live_sensor_b*active_sensors+active_resp_b)+api_athena*history_resp_kb*1024)/1073741824 -> 0.28647358 | D49: GB
A50: DynamoDB reads | B50: ddb_reads | C50: =live_polls+page_loads_month*2+tests_month*api_per_test -> 88272.333 | D50: read units | E50: /tests/active on every poll, test lists, comments
A51: DynamoDB writes | B51: ddb_writes | C51: =tests_month*ddb_writes_test -> 80 | D51: write units
A52: CloudFront requests | B52: cf_requests | C52: =page_loads_month*web_files -> 4562.5 | D52: requests
A53: CloudFront data out | B53: cf_gb | C53: =page_loads_month*web_kb*1024/1073741824 -> 0.013633569 | D53: GB
A54: S3 GETs from dashboard | B54: s3_get_dash | C54: =live_polls*2+page_loads_month*web_files+hours_open*12*days_month -> 182682.5 | D54: requests | E54: latest/data + latest/system per poll; web files (CloudFront caching disabled); config.json refresh every 5 min
A56: Athena (history, exports, reports)
A57: Scan per history/export query | B57: q_hist_b | C57: =MAX(athena_min_mb*1048576,raw_day_data*(history_days+1)) -> 11076480 | D57: bytes | E57: Whole dt= day partitions in the range (+1 boundary day), minimum 10 MB
A58: Days scanned per test report | B58: test_days | C58: =ROUNDUP(test_hours/24,0)+1 -> 2 | D58: days
A59: Scan per test report | B59: q_test_b | C59: =2*MAX(athena_min_mb*1048576,raw_day_data*test_days)+MAX(athena_min_mb*1048576,raw_day_sys*test_days) -> 32638720 | D59: bytes | E59: sensor_summary + data_gaps (data table) + system_summary
A60: Scan per weekly report | B60: q_week_b | C60: =2*MAX(athena_min_mb*1048576,raw_day_data*8)+MAX(athena_min_mb*1048576,raw_day_sys*8) -> 99097600 | D60: bytes | E60: Same 3 queries over 7 days (+1 boundary)
A61: Athena queries per month | B61: athena_queries | C61: =api_athena+3*reports_month -> 655.33333 | D61: queries
A62: Athena data scanned | B62: athena_tb | C62: =(api_athena*q_hist_b+tests_month*q_test_b+weekly_reports*q_week_b)/1099511627776 -> 0.0068571257 | D62: TB/month
A63: S3 GETs by Athena | B63: s3_get_athena | C63: =api_athena*(history_days+1)*objs_day_data+tests_month*test_days*(2*objs_day_data+objs_day_sys)+weekly_reports*8*(2*objs_day_data+objs_day_sys) -> 1999680 | D63: requests | E63: Athena reads every small Firehose object in the range; billed to the bucket owner
A64: S3 PUTs other | B64: s3_put_other | C64: =athena_queries*2+exports+reports_month*2 -> 1345.3333 | D64: requests | E64: Athena results (csv + metadata), exports, report files
A65: Glue catalog requests | B65: glue_requests | C65: =athena_queries*glue_per_query -> 2621.3333 | D65: requests
A66: CloudWatch log ingestion | B66: logs_gb | C66: =lambda_inv*log_kb*1024/1073741824 -> 0.084598303 | D66: GB/month
A67: CloudWatch log storage at retention horizon | B67: logs_store_gb | C67: =logs_gb*months_kept -> 1.0151796 | D67: GB | E67: No retention configured on the Lambda log groups
A70: Monthly cost per site (USD)
A71: Service | B71: Item | C71: Usage | D71: Usage unit | E71: Free allowance | F71: Billable | G71: Unit price | H71: Monthly cost
A72: IoT Core | B72: Connectivity (always connected) | C72: =1440*days_month/1000000 -> 0.0438 | D72: million conn-min | E72: =p_iot_conn_free*free_flag -> 0 | F72: =MAX(0,C72-E72) -> 0.0438 | G72: =p_iot_conn -> 0.08 | H72: =F72*G72 -> 0.003504
A73: IoT Core | B73: Messaging | C73: =iot_billed_month/1000000 -> 0.1752 | D73: million messages | E73: =p_iot_msg_free*free_flag -> 0 | F73: =MAX(0,C73-E73) -> 0.1752 | G73: =p_iot_msg -> 1 | H73: =F73*G73 -> 0.1752
A74: IoT Core | B74: Rules triggered | C74: =msgs_month/1000000 -> 0.1752 | D74: million rules | E74: =p_iot_rule_free*free_flag -> 0 | F74: =MAX(0,C74-E74) -> 0.1752 | G74: =p_iot_rule -> 0.15 | H74: =F74*G74 -> 0.02628
A75: IoT Core | B75: Rule actions (Firehose + S3 per message) | C75: =msgs_month*2/1000000 -> 0.3504 | D75: million actions | E75: =p_iot_action_free*free_flag -> 0 | F75: =MAX(0,C75-E75) -> 0.3504 | G75: =p_iot_action -> 0.15 | H75: =F75*G75 -> 0.05256
A76: Data Firehose | B76: Ingestion (5 KB rounding) | C76: =fh_gb_month -> 0.8354187 | D76: GB | E76: =p_fh_free*free_flag -> 0 | F76: =MAX(0,C76-E76) -> 0.8354187 | G76: =p_fh -> 0.029 | H76: =F76*G76 -> 0.024227142
A77: S3 | B77: PUT: latest/*.json on every message | C77: =latest_puts_month/1000 -> 175.2 | D77: 1,000 requests | E77: =p_s3_put_free*free_flag -> 0 | F77: =MAX(0,C77-E77) -> 175.2 | G77: =p_s3_put -> 0.005 | H77: =F77*G77 -> 0.876
A78: S3 | B78: PUT: Firehose objects | C78: =fh_puts_month/1000 -> 87.6 | D78: 1,000 requests | E78: =p_s3_put_free*free_flag -> 0 | F78: =MAX(0,C78-E78) -> 87.6 | G78: =p_s3_put -> 0.005 | H78: =F78*G78 -> 0.438
A79: S3 | B79: PUT: Athena results, exports, reports | C79: =s3_put_other/1000 -> 1.3453333 | D79: 1,000 requests | E79: =p_s3_put_free*free_flag -> 0 | F79: =MAX(0,C79-E79) -> 1.3453333 | G79: =p_s3_put -> 0.005 | H79: =F79*G79 -> 0.0067266667
A80: S3 | B80: GET: dashboard (live, web files, config) | C80: =s3_get_dash/1000 -> 182.6825 | D80: 1,000 requests | E80: =p_s3_get_free*free_flag -> 0 | F80: =MAX(0,C80-E80) -> 182.6825 | G80: =p_s3_get -> 0.0004 | H80: =F80*G80 -> 0.073073
A81: S3 | B81: GET: Athena reading raw objects | C81: =s3_get_athena/1000 -> 1999.68 | D81: 1,000 requests | E81: =p_s3_get_free*free_flag -> 0 | F81: =MAX(0,C81-E81) -> 1999.68 | G81: =p_s3_get -> 0.0004 | H81: =F81*G81 -> 0.799872
A82: S3 | B82: Storage (at retention horizon) | C82: =s3_store_gb -> 2.0906935 | D82: GB-month | E82: =p_s3_gb_free*free_flag -> 0 | F82: =MAX(0,C82-E82) -> 2.0906935 | G82: =p_s3_gb -> 0.023 | H82: =F82*G82 -> 0.04808595
A83: Athena | B83: Data scanned | C83: =athena_tb -> 0.0068571257 | D83: TB | E83: =p_athena_free*free_flag -> 0 | F83: =MAX(0,C83-E83) -> 0.0068571257 | G83: =p_athena -> 5 | H83: =F83*G83 -> 0.034285629
A84: Glue | B84: Data Catalog requests | C84: =glue_requests/1000000 -> 0.0026213333 | D84: million requests | E84: =p_glue_free*free_flag -> 0 | F84: =MAX(0,C84-E84) -> 0.0026213333 | G84: =p_glue -> 1 | H84: =F84*G84 -> 0.0026213333
A85: Lambda | B85: Requests | C85: =lambda_inv/1000000 -> 0.1774155 | D85: million requests | E85: =p_lambda_req_free*free_flag -> 0 | F85: =MAX(0,C85-E85) -> 0.1774155 | G85: =p_lambda_req -> 0.2 | H85: =F85*G85 -> 0.0354831
A86: Lambda | B86: Compute (arm64) | C86: =lambda_gbs -> 10445.908 | D86: GB-seconds | E86: =p_lambda_gbs_free*free_flag -> 0 | F86: =MAX(0,C86-E86) -> 10445.908 | G86: =p_lambda_gbs -> 1.33334e-05 | H86: =F86*G86 -> 0.13927947
A87: API Gateway | B87: REST requests | C87: =api_requests/1000000 -> 0.17740317 | D87: million requests | E87: =p_apigw_free*free_flag -> 0 | F87: =MAX(0,C87-E87) -> 0.17740317 | G87: =p_apigw -> 3.5 | H87: =F87*G87 -> 0.62091108
A88: DynamoDB | B88: Reads | C88: =ddb_reads/1000000 -> 0.088272333 | D88: million RRU | E88: =p_ddb_r_free*free_flag -> 0 | F88: =MAX(0,C88-E88) -> 0.088272333 | G88: =p_ddb_r -> 0.125 | H88: =F88*G88 -> 0.011034042
A89: DynamoDB | B89: Writes | C89: =ddb_writes/1000000 -> 8e-05 | D89: million WRU | E89: =p_ddb_w_free*free_flag -> 0 | F89: =MAX(0,C89-E89) -> 8e-05 | G89: =p_ddb_w -> 0.625 | H89: =F89*G89 -> 5e-05
A90: DynamoDB | B90: Storage | C90: =0.001 -> 0.001 | D90: GB-month | E90: =p_ddb_gb_free*free_flag -> 0 | F90: =MAX(0,C90-E90) -> 0.001 | G90: =p_ddb_gb -> 0.25 | H90: =F90*G90 -> 0.00025
A91: CloudFront | B91: HTTPS requests | C91: =cf_requests/1000000 -> 0.0045625 | D91: million requests | E91: =p_cf_req_free*free_flag -> 0 | F91: =MAX(0,C91-E91) -> 0.0045625 | G91: =p_cf_req -> 1 | H91: =F91*G91 -> 0.0045625
A92: CloudFront | B92: Data transfer out | C92: =cf_gb -> 0.013633569 | D92: GB | E92: =p_cf_gb_free*free_flag -> 0 | F92: =MAX(0,C92-E92) -> 0.013633569 | G92: =p_cf_gb -> 0.085 | H92: =F92*G92 -> 0.0011588534
A93: Data transfer | B93: API responses to internet | C93: =api_out_gb -> 0.28647358 | D93: GB | E93: =p_dto_free*free_flag -> 0 | F93: =MAX(0,C93-E93) -> 0.28647358 | G93: =p_dto -> 0.09 | H93: =F93*G93 -> 0.025782622
A94: CloudWatch Logs | B94: Ingestion | C94: =logs_gb -> 0.084598303 | D94: GB | E94: =p_cw_in_free*free_flag -> 0 | F94: =MAX(0,C94-E94) -> 0.084598303 | G94: =p_cw_in -> 0.5 | H94: =F94*G94 -> 0.042299151
A95: CloudWatch Logs | B95: Storage (at retention horizon) | C95: =logs_store_gb -> 1.0151796 | D95: GB-month | E95: =p_cw_gb_free*free_flag -> 0 | F95: =MAX(0,C95-E95) -> 1.0151796 | G95: =p_cw_gb -> 0.03 | H95: =F95*G95 -> 0.030455389
A96: EventBridge | B96: Weekly schedule | C96: =weekly_reports -> 4.3333333 | D96: invocations | E96: =p_eb_free*free_flag -> 0 | F96: =MAX(0,C96-E96) -> 4.3333333 | G96: =p_eb -> 0 | H96: =F96*G96 -> 0
A97: IAM / API keys / usage plan | B97: No charge | C97: =0 -> 0 | D97: - | E97: =p_free_free*free_flag -> 0 | F97: =MAX(0,C97-E97) -> 0 | G97: =p_free -> 0 | H97: =F97*G97 -> 0
A98: Total per site per month | H98: =SUM(H72:H97) -> 3.4717019
A99: Free allowances are per AWS account; with several sites the model applies them to each site, so leave the toggle on 'No' for a conservative multi-site figure.

Sheet Data Plan
A1: Cellular data plan per Pi (gateway → AWS IoT plus everything else the Pi does online)
A2: Blue = edit · black = formula · green = from another sheet. Sensor traffic comes from the Calculation sheet; the other lines are assumptions — measure the real usage on the Pi after a week (vnstat or /sys/class/net/<iface>/statistics).
A4: Item | B4: Name | C4: Value | D4: Unit | E4: Source / note
A6: Gateway traffic (sensor + system messages)
A7: Gateway MQTT traffic | B7: dp_gateway_mb | C7: =wire_month_mb -> 217.3356 | D7: MB/month | E7: Calculation sheet: payload + MQTT/TLS/TCP overhead + acks, for the active sensors and intervals
A9: Other traffic on the Pi (assumptions)
A10: MQTT reconnects | B10: dp_reconnects | C10: 5 | D10: per day | E10: Weak cellular signal → more reconnects. Each one repeats the TLS handshake
A11: Traffic per reconnect | B11: dp_reconnect_kb | C11: 7 | D11: KB | E11: TLS handshake with certificate chain + MQTT CONNECT
A12: TCP retransmissions | B12: dp_retrans_pct | C12: 0.1 | D12: % of gateway traffic | E12: Typically 5–15 % on cellular
A13: DNS + NTP time sync | B13: dp_dns_ntp_mb | C13: 5 | D13: MB/month | E13: Estimate
A14: Remote SSH / maintenance | B14: dp_ssh_mb | C14: 10 | D14: MB/month | E14: More if you copy logs or databases off the Pi
A15: Code/config updates (push_site.sh) | B15: dp_deploys | C15: 2 | D15: per month | E15: rsync of the Akvo_Green code + config.json
A16: Traffic per update | B16: dp_deploy_mb | C16: 3 | D16: MB | E16: Estimate; rsync only sends changed files
A17: OS updates (apt / unattended-upgrades) | B17: dp_os_mb | C17: 0 | D17: MB/month | E17: 0 = automatic updates disabled and done over Wi-Fi/Ethernet. If left on, budget 300+ MB (a kernel/firmware update alone can exceed this)
A18: Carrier minimum billed per session | B18: dp_session_min_kb | C18: 0 | D18: KB | E18: 0 = billed by actual usage. Some M2M plans round each data session up (e.g. 100 KB); every reconnect starts a new session
A19: Safety margin | B19: dp_margin | C19: 0.3 | D19: % | E19: Headroom for unexpected traffic and month-to-month variation
A21: Monthly data needed per Pi
A22: Reconnects | B22: dp_reconnect_mb | C22: =dp_reconnects*dp_reconnect_kb*days_month/1000 -> 1.0645833 | D22: MB/month | E22: Reconnects × KB × days
A23: Retransmissions | B23: dp_retrans_mb | C23: =dp_gateway_mb*dp_retrans_pct -> 21.73356 | D23: MB/month | E23: Gateway traffic × %
A24: Updates | B24: dp_updates_mb | C24: =dp_deploys*dp_deploy_mb+dp_os_mb -> 6 | D24: MB/month | E24: Code updates + OS updates
A25: Carrier session rounding | B25: dp_rounding_mb | C25: =dp_reconnects*days_month*MAX(0,dp_session_min_kb-dp_reconnect_kb)/1000 -> 0 | D25: MB/month | E25: Extra billed when each session is rounded up to the carrier minimum
A26: Subtotal | B26: dp_subtotal_mb | C26: =dp_gateway_mb+dp_reconnect_mb+dp_retrans_mb+dp_dns_ntp_mb+dp_ssh_mb+dp_updates_mb+dp_rounding_mb -> 261.13374 | D26: MB/month
A27: Data needed per Pi (with margin) | B27: dp_required_mb | C27: =dp_subtotal_mb*(1+dp_margin) -> 339.47387 | D27: MB/month | E27: Size the plan with this
A28: Per day | B28: dp_required_day_mb | C28: =dp_required_mb/days_month -> 11.160785 | D28: MB/day
A29: All Pis (× sites) | B29: dp_required_all_gb | C29: =dp_required_mb*sites/1000 -> 0.33947387 | D29: GB/month | E29: If the SIMs share a pooled plan
A31: Plan options (list from smallest to largest; enter your carrier's plans and prices)
A32: Currency | B32: dp_currency | C32: MXN | D32: text | E32: Currency of the prices below
A34: Plan | B34: Data (MB/month) | C34: Price / month | D34: Fits? | E34: Headroom
A35: 250 MB | B35: 250 | D35: =IF(B35>=dp_required_mb,"Yes","No") -> No | E35: =IFERROR(B35/dp_required_mb-1,0) -> -0.26356629
A36: 500 MB | B36: 500 | D36: =IF(B36>=dp_required_mb,"Yes","No") -> Yes | E36: =IFERROR(B36/dp_required_mb-1,0) -> 0.47286743
A37: 1 GB | B37: 1000 | D37: =IF(B37>=dp_required_mb,"Yes","No") -> Yes | E37: =IFERROR(B37/dp_required_mb-1,0) -> 1.9457349
A38: 2 GB | B38: 2000 | D38: =IF(B38>=dp_required_mb,"Yes","No") -> Yes | E38: =IFERROR(B38/dp_required_mb-1,0) -> 4.8914697
A39: 3 GB | B39: 3000 | D39: =IF(B39>=dp_required_mb,"Yes","No") -> Yes | E39: =IFERROR(B39/dp_required_mb-1,0) -> 7.8372046
A40: 5 GB | B40: 5000 | D40: =IF(B40>=dp_required_mb,"Yes","No") -> Yes | E40: =IFERROR(B40/dp_required_mb-1,0) -> 13.728674
A41: Price column left empty = unknown; fill in your carrier's offer to see the monthly cost.
A43: Recommended plan per Pi | B43: dp_plan | C43: =IF(dp_required_mb<=MAX('Data Plan'!$B$35:$B$40),INDEX('Data Plan'!$A$35:$A$40,COUNTIF('Data Plan'!$B$35:$B$40,"<"&dp_required_mb)+1),"Larger than the listed plans") -> 500 MB | E43: Smallest listed plan that covers the data needed
A44: Plan size | B44: dp_plan_mb | C44: =IF(dp_required_mb<=MAX('Data Plan'!$B$35:$B$40),INDEX('Data Plan'!$B$35:$B$40,COUNTIF('Data Plan'!$B$35:$B$40,"<"&dp_required_mb)+1),0) -> 500 | D44: MB/month
A45: Plan price per Pi | B45: dp_plan_price | C45: =IF(dp_required_mb<=MAX('Data Plan'!$B$35:$B$40),INDEX('Data Plan'!$C$35:$C$40,COUNTIF('Data Plan'!$B$35:$B$40,"<"&dp_required_mb)+1),0) -> 0 | D45: per month | E45: In the currency above
A46: Plan price, all Pis | B46: dp_plan_price_all | C46: =dp_plan_price*sites -> 0 | D46: per month | E46: × number of sites
